CHANGELOG.rst
MANIFEST.in
README.md
setup.cfg
setup.py
Zambi.egg-info/PKG-INFO
Zambi.egg-info/SOURCES.txt
Zambi.egg-info/dependency_links.txt
Zambi.egg-info/not-zip-safe
Zambi.egg-info/requires.txt
Zambi.egg-info/top_level.txt
zambi/__init__.py