Metadata-Version: 1.1
Name: Zambi
Version: 1.0.0
Summary: Zambi Connection Manager
Home-page: UNKNOWN
Author: Jesse Escobedo
Author-email: jesse.escobedo@citygridmedia.com
License: Apache
Keywords: Zambi AWS devops
Platform: UNKNOWN
Classifier: Programming Language :: Python
Classifier: Programming Language :: Python :: 2.6
Classifier: Programming Language :: Python :: 2.7
Classifier: Intended Audience :: System Administrators 
